torchpipe/__init__.py
torchpipe/extension.py
torchpipe/load_libs.py
torchpipe/load_omniback.py
torchpipe/csrc/helper/dlpack_helper.cpp
torchpipe/csrc/helper/dlpack_helper.hpp
torchpipe/csrc/helper/mat.cpp
torchpipe/csrc/helper/mat.hpp
torchpipe/csrc/helper/net_info.cpp
torchpipe/csrc/helper/net_info.hpp
torchpipe/csrc/helper/task_keys.hpp
torchpipe/csrc/helper/torch.cpp
torchpipe/csrc/helper/torch.hpp
torchpipe/csrc/mat_torch/CvtColorMat.cpp
torchpipe/csrc/mat_torch/CvtColorMat.hpp
torchpipe/csrc/mat_torch/DecodeMat.cpp
torchpipe/csrc/mat_torch/DecodeMat.hpp
torchpipe/csrc/mat_torch/ResizeMat.cpp
torchpipe/csrc/mat_torch/ResizeMat.hpp
torchpipe/csrc/mat_torch/converts.cpp
torchpipe/csrc/mat_torch/converts.hpp
torchpipe/csrc/mat_torch/mat2tensor.hpp
torchpipe/csrc/nvjpeg_torch/DecodeTensor.cpp
torchpipe/csrc/nvjpeg_torch/DecodeTensor.hpp
torchpipe/csrc/nvjpeg_torch/README.md
torchpipe/csrc/tensorrt_torch/TensorrtInferTensor.cpp
torchpipe/csrc/tensorrt_torch/TensorrtInferTensor.hpp
torchpipe/csrc/tensorrt_torch/TensorrtTensor.cpp
torchpipe/csrc/tensorrt_torch/TensorrtTensor.hpp
torchpipe/csrc/tensorrt_torch/aes.cpp
torchpipe/csrc/tensorrt_torch/aes.h
torchpipe/csrc/tensorrt_torch/allocator.cpp
torchpipe/csrc/tensorrt_torch/allocator.hpp
torchpipe/csrc/tensorrt_torch/encrypt.cpp
torchpipe/csrc/tensorrt_torch/encrypt.hpp
torchpipe/csrc/tensorrt_torch/model.cpp
torchpipe/csrc/tensorrt_torch/model.hpp
torchpipe/csrc/tensorrt_torch/tensorrt_helper.cpp
torchpipe/csrc/tensorrt_torch/tensorrt_helper.hpp
torchpipe/csrc/tensorrt_torch/tensorrt_plugins.cpp
torchpipe/csrc/tensorrt_torch/tensorrt_plugins.hpp
torchpipe/csrc/tensorrt_torch/tensorrt_plugins_anchor.cpp_
torchpipe/csrc/tensorrt_torch/tensorrt_plugins_anchor.hpp
torchpipe/csrc/torchplugins/CropTensor.cpp
torchpipe/csrc/torchplugins/CropTensor.hpp
torchpipe/csrc/torchplugins/CvtColorTensor.cpp
torchpipe/csrc/torchplugins/CvtColorTensor.hpp
torchpipe-0.1.22.dist-info/METADATA
torchpipe-0.1.22.dist-info/WHEEL
torchpipe-0.1.22.dist-info/top_level.txt
torchpipe-0.1.22.dist-info/RECORD
torchpipe-0.1.22.dist-info/licenses/LICENSE
