Metadata-Version: 2.4
Name: torchpipe
Version: 0.1.22
Summary: Serving inside Pytorch
Author: torchpipe team
License: Apache-2.0
Classifier: Development Status :: 4 - Beta
Classifier: Intended Audience :: Developers
Classifier: Intended Audience :: Education
Classifier: Intended Audience :: Science/Research
Requires-Python: >=3.8
License-File: LICENSE
Requires-Dist: torch
Requires-Dist: omniback==0.1.22
Requires-Dist: setuptools
Requires-Dist: packaging
Requires-Dist: tqdm
Requires-Dist: requests
Requires-Dist: ninja
Requires-Dist: cmake
Provides-Extra: test
Requires-Dist: onnx-graphsurgeon>=0.5.8; extra == "test"
Requires-Dist: onnxslim; extra == "test"
Requires-Dist: pytest; extra == "test"
Dynamic: license-file
